bulma/__init__.py
bulma/main.html
bulma/mkdocs_theme.yml
bulma/assets/css/bulma.min.css
bulma/partials/navbar.html
bulma/partials/sidebar-item.html
bulma/partials/sidebar.html
mkdocs_bulma-0.0.5.dist-info/LICENSE
mkdocs_bulma-0.0.5.dist-info/METADATA
mkdocs_bulma-0.0.5.dist-info/WHEEL
mkdocs_bulma-0.0.5.dist-info/entry_points.txt
mkdocs_bulma-0.0.5.dist-info/top_level.txt
mkdocs_bulma-0.0.5.dist-info/RECORD
