Metadata-Version: 2.1
Name: mkdocs-bulma
Version: 0.0.5
Summary: Bulma for mkdocs
Home-page: https://github.com/rajasimon/mkdocs-bulma
Author: Raja Simon
Author-email: rajasimon@icloud.com
License: MIT
Platform: UNKNOWN
